COPYING
COPYING.lesser
MANIFEST.in
NOTICE
README.md
requirements.txt
setup.py
compiler/__init__.py
compiler/api/__init__.py
compiler/api/compiler.py
compiler/api/source/auth_key.tl
compiler/api/source/main_api.tl
compiler/api/source/sys_msgs.tl
compiler/api/template/combinator.txt
compiler/api/template/type.txt
compiler/errors/__init__.py
compiler/errors/compiler.py
compiler/errors/sort.py
compiler/errors/source/303_SEE_OTHER.tsv
compiler/errors/source/400_BAD_REQUEST.tsv
compiler/errors/source/401_UNAUTHORIZED.tsv
compiler/errors/source/403_FORBIDDEN.tsv
compiler/errors/source/406_NOT_ACCEPTABLE.tsv
compiler/errors/source/420_FLOOD.tsv
compiler/errors/source/500_INTERNAL_SERVER_ERROR.tsv
compiler/errors/source/503_SERVICE_UNAVAILABLE.tsv
compiler/errors/template/class.txt
compiler/errors/template/sub_class.txt
mixdev.egg-info/PKG-INFO
mixdev.egg-info/SOURCES.txt
mixdev.egg-info/dependency_links.txt
mixdev.egg-info/not-zip-safe
mixdev.egg-info/requires.txt
mixdev.egg-info/top_level.txt
tests/__init__.py
tests/test_file_id.py
tests/filters/__init__.py
tests/filters/test_command.py
tests/parser/__init__.py
tests/parser/test_html.py
thegokil/__init__.py
thegokil/client.py
thegokil/dispatcher.py
thegokil/emoji.py
thegokil/file_id.py
thegokil/filters.py
thegokil/mime_types.py
thegokil/py.typed
thegokil/sync.py
thegokil/utils.py
thegokil/connection/__init__.py
thegokil/connection/connection.py
thegokil/connection/transport/__init__.py
thegokil/connection/transport/tcp/__init__.py
thegokil/connection/transport/tcp/tcp.py
thegokil/connection/transport/tcp/tcp_abridged.py
thegokil/connection/transport/tcp/tcp_abridged_o.py
thegokil/connection/transport/tcp/tcp_full.py
thegokil/connection/transport/tcp/tcp_intermediate.py
thegokil/connection/transport/tcp/tcp_intermediate_o.py
thegokil/crypto/__init__.py
thegokil/crypto/aes.py
thegokil/crypto/mtproto.py
thegokil/crypto/prime.py
thegokil/crypto/rsa.py
thegokil/enums/__init__.py
thegokil/enums/auto_name.py
thegokil/enums/chat_action.py
thegokil/enums/chat_event_action.py
thegokil/enums/chat_member_status.py
thegokil/enums/chat_members_filter.py
thegokil/enums/chat_type.py
